sitecustomize.py
powertrace_hooks-0.1.1.dist-info/LICENSE
powertrace_hooks-0.1.1.dist-info/METADATA
powertrace_hooks-0.1.1.dist-info/WHEEL
powertrace_hooks-0.1.1.dist-info/entry_points.txt
powertrace_hooks-0.1.1.dist-info/top_level.txt
powertrace_hooks-0.1.1.dist-info/RECORD
