Metadata-Version: 2.1
Name: powertrace-hooks
Version: 0.1.1
Summary: Automated stack trace logging and visualization
Author-email: Quinten Roets <qdr2104@columbia.edu>
License: MIT
Project-URL: Source Code, https://github.com/quintenroets/powertrace-hooks
Requires-Python: >=3.10
License-File: LICENSE
Requires-Dist: powertrace <1,>=0.1.1
Provides-Extra: dev
Requires-Dist: package-dev-tools <1,>=0.5.11 ; extra == 'dev'
Requires-Dist: package-dev-utils <1,>=0.1.6 ; extra == 'dev'
